{"message":"success","stations":[{"_id":"6034129f8f2bb86af91e14eb","placeId":"00c22ec144b14bdb12142febbdd14b2297a175f6e8d45180d6d93a294e77503c","CO":0.427,"NO2":1.133,"OZONE":41.822,"PM10":4.588,"PM25":42.627,"SO2":0.249,"city":"","countryCode":"IN","division":"Dhanbad","lat":23.79565,"lng":86.43039,"placeName":"Nawagarh","postalCode":"828306","state":"Jharkhand","updatedAt":"2022-05-26 08:00:00","AQI":119,"aqiInfo":{"pollutant":"PM2.5","concentration":42.627,"category":"Unhealthy for Sensitive Groups"}}]}