{"message":"success","stations":[{"_id":"6034129a8f2bb86af91d952b","placeId":"94f86a5ff0d8c984f2daddfeb810c82863c5e6f7ab9d7a23a237ccea705c5777","CO":0.426,"NO2":11.092,"OZONE":34.951,"PM10":141.298,"PM25":37.431,"SO2":4.703,"city":"Indore","countryCode":"IN","division":"Khandwa (East Nimar)","lat":21.832485000000002,"lng":76.358853,"placeName":"Ganesh Talai Khandwa","postalCode":"450001","state":"Madhya Pradesh","updatedAt":"2022-05-26 08:00:00","AQI":106,"aqiInfo":{"pollutant":"PM2.5","concentration":37.431,"category":"Unhealthy for Sensitive Groups"}}]}