{"message":"success","stations":[{"_id":"6034128d8f2bb86af91c1a12","placeId":"370d3861bf8d6627d3477e2c3596dfb00025ddf0ff814f533af3c19bb67f83b7","CO":0.328,"NO2":10.525,"OZONE":8.301,"PM10":84.2,"PM25":40.12,"SO2":4.817,"city":"","countryCode":"IN","division":"Pulwama","lat":33.644991,"lng":75.01803100000001,"placeName":"Kulgam","postalCode":"192231","state":"Jammu and Kashmir","updatedAt":"2022-05-26 08:00:00","AQI":112,"aqiInfo":{"pollutant":"PM2.5","concentration":40.12,"category":"Unhealthy for Sensitive Groups"}}]}