{"message":"success","stations":[{"_id":"603412908f2bb86af91c6e29","placeId":"7ced949fda99ffe205597a21f1a56fa212866ef1fcf204043914eb183fffb0ae","CO":0.801,"NO2":9.49,"OZONE":38.941,"PM10":129.843,"PM25":36.393,"SO2":7.653,"city":"Amravati","countryCode":"IN","division":"Yavatmal","lat":20.387092000000003,"lng":78.124773,"placeName":"Zillla Parishad","postalCode":"445002","state":"Maharashtra","updatedAt":"2022-05-26 08:00:00","AQI":103,"aqiInfo":{"pollutant":"PM2.5","concentration":36.393,"category":"Unhealthy for Sensitive Groups"}}]}